[
{
  "name":"loaders.AppLoader"
},
{
  "name":"[B"
},
{
  "name":"akka.actor.ActorCell",
  "allDeclaredFields":true,
  "fields":[
    {"name":"akka$actor$dungeon$Children$$_childrenRefsDoNotCallMeDirectly", "allowUnsafeAccess":true}, 
    {"name":"akka$actor$dungeon$Children$$_functionRefsDoNotCallMeDirectly", "allowUnsafeAccess":true}, 
    {"name":"akka$actor$dungeon$Children$$_nextNameDoNotCallMeDirectly", "allowUnsafeAccess":true}, 
    {"name":"akka$actor$dungeon$Dispatch$$_mailboxDoNotCallMeDirectly", "allowUnsafeAccess":true}
  ]
},
{
  "name":"akka.actor.DefaultSupervisorStrategy",
  "methods":[{"name":"<init>","parameterTypes":[] }]
},
{
  "name":"akka.actor.LightArrayRevolverScheduler",
  "methods":[{"name":"<init>","parameterTypes":["com.typesafe.config.Config","akka.event.LoggingAdapter","java.util.concurrent.ThreadFactory"] }]
},
{
  "name":"akka.actor.LightArrayRevolverScheduler$TaskHolder",
  "fields":[{"name":"task", "allowUnsafeAccess":true}]
},
{
  "name":"akka.actor.LocalActorRefProvider",
  "methods":[{"name":"<init>","parameterTypes":["java.lang.String","akka.actor.ActorSystem$Settings","akka.event.EventStream","akka.actor.DynamicAccess"] }]
},
{
  "name":"akka.actor.LocalActorRefProvider$Guardian",
  "allDeclaredFields":true,
  "allDeclaredConstructors":true
},
{
  "name":"akka.actor.LocalActorRefProvider$SystemGuardian",
  "allDeclaredFields":true,
  "allDeclaredConstructors":true
},
{
  "name":"akka.actor.Props$EmptyActor",
  "methods":[{"name":"<init>","parameterTypes":[] }]
},
{
  "name":"akka.actor.RepointableActorRef",
  "fields":[
    {"name":"_cellDoNotCallMeDirectly", "allowUnsafeAccess":true}, 
    {"name":"_lookupDoNotCallMeDirectly", "allowUnsafeAccess":true}
  ]
},
{
  "name":"akka.actor.typed.ActorRef"
},
{
  "name":"akka.actor.typed.internal.MiscMessageSerializer",
  "methods":[{"name":"<init>","parameterTypes":["akka.actor.ExtendedActorSystem"] }]
},
{
  "name":"akka.actor.typed.internal.adapter.ActorAdapter",
  "allDeclaredFields":true
},
{
  "name":"akka.actor.typed.internal.adapter.ActorRefAdapter"
},
{
  "name":"akka.actor.typed.internal.adapter.ActorSystemAdapter$LoadTypedExtensions$",
  "fields":[{"name":"MODULE$"}]
},
{
  "name":"akka.actor.typed.internal.receptionist.DefaultServiceKey"
},
{
  "name":"akka.actor.typed.internal.receptionist.ServiceKeySerializer",
  "methods":[{"name":"<init>","parameterTypes":["akka.actor.ExtendedActorSystem"] }]
},
{
  "name":"akka.actor.typed.receptionist.Receptionist$",
  "fields":[{"name":"MODULE$"}]
},
{
  "name":"akka.dispatch.AbstractNodeQueue",
  "fields":[{"name":"_tailDoNotCallMeDirectly", "allowUnsafeAccess":true}]
},
{
  "name":"akka.dispatch.AbstractNodeQueue$Node",
  "fields":[{"name":"_nextDoNotCallMeDirectly", "allowUnsafeAccess":true}]
},
{
  "name":"akka.dispatch.BoundedControlAwareMessageQueueSemantics"
},
{
  "name":"akka.dispatch.BoundedDequeBasedMessageQueueSemantics"
},
{
  "name":"akka.dispatch.BoundedMessageQueueSemantics"
},
{
  "name":"akka.dispatch.ControlAwareMessageQueueSemantics"
},
{
  "name":"akka.dispatch.DequeBasedMessageQueueSemantics"
},
{
  "name":"akka.dispatch.Mailbox",
  "fields":[
    {"name":"_statusDoNotCallMeDirectly", "allowUnsafeAccess":true}, 
    {"name":"_systemQueueDoNotCallMeDirectly", "allowUnsafeAccess":true}
  ]
},
{
  "name":"akka.dispatch.MessageDispatcher",
  "fields":[
    {"name":"_inhabitantsDoNotCallMeDirectly", "allowUnsafeAccess":true}, 
    {"name":"_shutdownScheduleDoNotCallMeDirectly", "allowUnsafeAccess":true}
  ]
},
{
  "name":"akka.dispatch.MultipleConsumerSemantics"
},
{
  "name":"akka.dispatch.SingleConsumerOnlyUnboundedMailbox",
  "methods":[{"name":"<init>","parameterTypes":["akka.actor.ActorSystem$Settings","com.typesafe.config.Config"] }]
},
{
  "name":"akka.dispatch.UnboundedControlAwareMessageQueueSemantics"
},
{
  "name":"akka.dispatch.UnboundedDequeBasedMessageQueueSemantics"
},
{
  "name":"akka.dispatch.UnboundedMailbox",
  "methods":[{"name":"<init>","parameterTypes":["akka.actor.ActorSystem$Settings","com.typesafe.config.Config"] }]
},
{
  "name":"akka.dispatch.UnboundedMessageQueueSemantics"
},
{
  "name":"akka.event.EventStreamUnsubscriber",
  "allDeclaredFields":true,
  "allDeclaredConstructors":true
},
{
  "name":"akka.event.LoggerMailboxType",
  "methods":[{"name":"<init>","parameterTypes":["akka.actor.ActorSystem$Settings","com.typesafe.config.Config"] }]
},
{
  "name":"akka.event.LoggerMessageQueueSemantics"
},
{
  "name":"akka.event.slf4j.Slf4jLogger",
  "allDeclaredFields":true,
  "methods":[{"name":"<init>","parameterTypes":[] }]
},
{
  "name":"akka.event.slf4j.Slf4jLoggingFilter",
  "methods":[{"name":"<init>","parameterTypes":["akka.actor.ActorSystem$Settings","akka.event.EventStream"] }]
},
{
  "name":"akka.http.impl.engine.client.PoolMasterActor",
  "allDeclaredFields":true,
  "methods":[{"name":"<init>","parameterTypes":[] }]
},
{
  "name":"akka.io.SelectionHandler",
  "allDeclaredFields":true,
  "allDeclaredConstructors":true
},
{
  "name":"akka.io.SelectionHandler$SelectorBasedManager",
  "allDeclaredFields":true
},
{
  "name":"akka.io.TcpConnection",
  "allDeclaredFields":true
},
{
  "name":"akka.io.TcpIncomingConnection",
  "allDeclaredFields":true,
  "allDeclaredConstructors":true
},
{
  "name":"akka.io.TcpListener",
  "allDeclaredFields":true,
  "allDeclaredConstructors":true
},
{
  "name":"akka.io.TcpManager",
  "allDeclaredFields":true,
  "allDeclaredConstructors":true
},
{
  "name":"akka.pattern.PromiseActorRef",
  "fields":[
    {"name":"_stateDoNotCallMeDirectly", "allowUnsafeAccess":true}, 
    {"name":"_watchedByDoNotCallMeDirectly", "allowUnsafeAccess":true}
  ]
},
{
  "name":"akka.routing.ConsistentHashingPool",
  "methods":[{"name":"<init>","parameterTypes":["com.typesafe.config.Config"] }]
},
{
  "name":"akka.routing.RoundRobinPool",
  "methods":[{"name":"<init>","parameterTypes":["com.typesafe.config.Config"] }]
},
{
  "name":"akka.routing.RoutedActorCell$RouterActorCreator",
  "allDeclaredConstructors":true
},
{
  "name":"akka.routing.RouterActor",
  "allDeclaredFields":true
},
{
  "name":"akka.routing.RouterPoolActor",
  "allDeclaredFields":true
},
{
  "name":"akka.serialization.BooleanSerializer",
  "methods":[{"name":"<init>","parameterTypes":["akka.actor.ExtendedActorSystem"] }]
},
{
  "name":"akka.serialization.ByteArraySerializer",
  "methods":[{"name":"<init>","parameterTypes":["akka.actor.ExtendedActorSystem"] }]
},
{
  "name":"akka.serialization.ByteStringSerializer",
  "methods":[{"name":"<init>","parameterTypes":["akka.actor.ExtendedActorSystem"] }]
},
{
  "name":"akka.serialization.DisabledJavaSerializer",
  "methods":[{"name":"<init>","parameterTypes":["akka.actor.ExtendedActorSystem"] }]
},
{
  "name":"akka.serialization.IntSerializer",
  "methods":[{"name":"<init>","parameterTypes":["akka.actor.ExtendedActorSystem"] }]
},
{
  "name":"akka.serialization.LongSerializer",
  "methods":[{"name":"<init>","parameterTypes":["akka.actor.ExtendedActorSystem"] }]
},
{
  "name":"akka.serialization.SerializationExtension$",
  "fields":[{"name":"MODULE$"}]
},
{
  "name":"akka.serialization.StringSerializer",
  "methods":[{"name":"<init>","parameterTypes":["akka.actor.ExtendedActorSystem"] }]
},
{
  "name":"akka.serialization.jackson.AkkaJacksonModule",
  "methods":[{"name":"<init>","parameterTypes":[] }]
},
{
  "name":"akka.serialization.jackson.AkkaStreamJacksonModule",
  "methods":[{"name":"<init>","parameterTypes":[] }]
},
{
  "name":"akka.serialization.jackson.AkkaTypedJacksonModule",
  "methods":[{"name":"<init>","parameterTypes":[] }]
},
{
  "name":"akka.serialization.jackson.JacksonCborSerializer",
  "methods":[{"name":"<init>","parameterTypes":["akka.actor.ExtendedActorSystem","java.lang.String"] }]
},
{
  "name":"akka.serialization.jackson.JacksonJsonSerializer",
  "methods":[{"name":"<init>","parameterTypes":["akka.actor.ExtendedActorSystem","java.lang.String"] }]
},
{
  "name":"akka.stream.Graph"
},
{
  "name":"akka.stream.SinkRef"
},
{
  "name":"akka.stream.SourceRef"
},
{
  "name":"akka.stream.SystemMaterializer$",
  "fields":[{"name":"MODULE$"}]
},
{
  "name":"akka.stream.impl.MaterializerGuardian",
  "allDeclaredFields":true
},
{
  "name":"akka.stream.impl.StreamSupervisor",
  "allDeclaredFields":true
},
{
  "name":"akka.stream.impl.fusing.ActorGraphInterpreter",
  "allDeclaredFields":true
},
{
  "name":"akka.stream.impl.streamref.StreamRefsProtocol"
},
{
  "name":"akka.stream.serialization.StreamRefSerializer",
  "methods":[{"name":"<init>","parameterTypes":["akka.actor.ExtendedActorSystem"] }]
},
{
  "name":"akka.util.ByteString$ByteString1"
},
{
  "name":"akka.util.ByteString$ByteString1C"
},
{
  "name":"akka.util.ByteString$ByteStrings"
},
{
  "name":"com.fasterxml.jackson.databind.ext.Java7SupportImpl",
  "methods":[{"name":"<init>","parameterTypes":[] }]
},
{
  "name":"com.fasterxml.jackson.datatype.jdk8.Jdk8Module",
  "methods":[{"name":"<init>","parameterTypes":[] }]
},
{
  "name":"com.fasterxml.jackson.datatype.jsr310.JavaTimeModule",
  "methods":[{"name":"<init>","parameterTypes":[] }]
},
{
  "name":"com.fasterxml.jackson.module.paramnames.ParameterNamesModule",
  "methods":[{"name":"<init>","parameterTypes":[] }]
},
{
  "name":"com.fasterxml.jackson.module.scala.DefaultScalaModule",
  "methods":[{"name":"<init>","parameterTypes":[] }]
},
{
  "name":"com.google.common.base.internal.Finalizer",
  "methods":[{"name":"startFinalizer","parameterTypes":["java.lang.Class","java.lang.ref.ReferenceQueue","java.lang.ref.PhantomReference"] }]
},
{
  "name":"com.typesafe.sslconfig.ssl.NoopHostnameVerifier",
  "methods":[{"name":"<init>","parameterTypes":[] }]
},
{
  "name":"java.io.Serializable"
},
{
  "name":"java.lang.Boolean"
},
{
  "name":"java.lang.Integer"
},
{
  "name":"java.lang.Long"
},
{
  "name":"java.lang.String",
  "fields":[{"name":"value", "allowUnsafeAccess":true}]
},
{
  "name":"java.lang.Thread",
  "methods":[{"name":"<init>","parameterTypes":["java.lang.ThreadGroup","java.lang.Runnable","java.lang.String","long","boolean"] }]
},
{
  "name":"java.lang.invoke.VarHandle"
},
{
  "name":"loaders.AppLoader",
  "methods":[{"name":"<init>","parameterTypes":[] }]
},
{
  "name":"play.core.server.AkkaHttpServerProvider",
  "methods":[{"name":"<init>","parameterTypes":[] }]
},
{
  "name":"scala.Boolean"
},
{
  "name":"scala.Int"
},
{
  "name":"scala.Long"
},
{
  "name":"scala.Symbol"
},
{
  "name":"scala.concurrent.ExecutionContext$parasitic$",
  "fields":[{"name":"MODULE$"}]
},
{
  "name":"sun.misc.Unsafe",
  "allDeclaredFields":true
}
]
